{"nodes": [{"id": "lib_usd_brl_ts", "label": "usd-brl.ts", "file_type": "code", "source_file": "lib\\usd-brl.ts", "source_location": "L1"}, {"id": "usd_brl_ensureschema", "label": "ensureSchema()", "file_type": "code", "source_file": "lib\\usd-brl.ts", "source_location": "L10"}, {"id": "usd_brl_fetchawesomeapidaily", "label": "fetchAwesomeApiDaily()", "file_type": "code", "source_file": "lib\\usd-brl.ts", "source_location": "L25"}, {"id": "usd_brl_fetchbcbptax", "label": "fetchBcbPtax()", "file_type": "code", "source_file": "lib\\usd-brl.ts", "source_location": "L46"}, {"id": "usd_brl_upsertrates", "label": "upsertRates()", "file_type": "code", "source_file": "lib\\usd-brl.ts", "source_location": "L70"}, {"id": "usd_brl_getusdtobrl", "label": "getUsdToBrl()", "file_type": "code", "source_file": "lib\\usd-brl.ts", "source_location": "L98"}], "edges": [{"source": "lib_usd_brl_ts", "target": "db", "relation": "imports_from", "confidence": "EXTRACTED", "source_file": "lib\\usd-brl.ts", "source_location": "L1", "weight": 1.0}, {"source": "lib_usd_brl_ts", "target": "usd_brl_ensureschema", "relation": "contains", "confidence": "EXTRACTED", "source_file": "lib\\usd-brl.ts", "source_location": "L10", "weight": 1.0}, {"source": "lib_usd_brl_ts", "target": "usd_brl_fetchawesomeapidaily", "relation": "contains", "confidence": "EXTRACTED", "source_file": "lib\\usd-brl.ts", "source_location": "L25", "weight": 1.0}, {"source": "lib_usd_brl_ts", "target": "usd_brl_fetchbcbptax", "relation": "contains", "confidence": "EXTRACTED", "source_file": "lib\\usd-brl.ts", "source_location": "L46", "weight": 1.0}, {"source": "lib_usd_brl_ts", "target": "usd_brl_upsertrates", "relation": "contains", "confidence": "EXTRACTED", "source_file": "lib\\usd-brl.ts", "source_location": "L70", "weight": 1.0}, {"source": "lib_usd_brl_ts", "target": "usd_brl_getusdtobrl", "relation": "contains", "confidence": "EXTRACTED", "source_file": "lib\\usd-brl.ts", "source_location": "L98", "weight": 1.0}, {"source": "usd_brl_getusdtobrl", "target": "usd_brl_ensureschema", "relation": "calls", "confidence": "EXTRACTED", "source_file": "lib\\usd-brl.ts", "source_location": "L99", "weight": 1.0}, {"source": "usd_brl_getusdtobrl", "target": "usd_brl_fetchawesomeapidaily", "relation": "calls", "confidence": "EXTRACTED", "source_file": "lib\\usd-brl.ts", "source_location": "L126", "weight": 1.0}, {"source": "usd_brl_getusdtobrl", "target": "usd_brl_upsertrates", "relation": "calls", "confidence": "EXTRACTED", "source_file": "lib\\usd-brl.ts", "source_location": "L127", "weight": 1.0}, {"source": "usd_brl_getusdtobrl", "target": "usd_brl_fetchbcbptax", "relation": "calls", "confidence": "EXTRACTED", "source_file": "lib\\usd-brl.ts", "source_location": "L141", "weight": 1.0}]}